README.rst
setup.py
wishbone_input_amqp/__init__.py
wishbone_input_amqp/amqpin.py
wishbone_input_amqp.egg-info/PKG-INFO
wishbone_input_amqp.egg-info/SOURCES.txt
wishbone_input_amqp.egg-info/dependency_links.txt
wishbone_input_amqp.egg-info/entry_points.txt
wishbone_input_amqp.egg-info/namespace_packages.txt
wishbone_input_amqp.egg-info/not-zip-safe
wishbone_input_amqp.egg-info/requires.txt
wishbone_input_amqp.egg-info/top_level.txt